setup.py
Sanescript.egg-info/PKG-INFO
Sanescript.egg-info/SOURCES.txt
Sanescript.egg-info/dependency_links.txt
Sanescript.egg-info/requires.txt
Sanescript.egg-info/top_level.txt
sanescript/__init__.py
sanescript/config.py
sanescript/main.py
sanescript/parsing.py
sanescript/processing.py
sanescript/script.py