Metadata-Version: 1.0
Name: Sanescript
Version: 0.6.1
Summary: Library for creating scripts with sub-commands, and options from the command
Home-page: UNKNOWN
Author: Ali Afshar
Author-email: aafshar@gmail.com
License: UNKNOWN
Platform: UNKNOWN
